LICENSE.md
MANIFEST.in
README.rst
setup.py
pytassim/__init__.py
pytassim/observation.py
pytassim/state.py
pytassim/assimilation/__init__.py
pytassim/assimilation/base.py
pytassim/assimilation/utils.py
pytassim/assimilation/filter/__init__.py
pytassim/assimilation/filter/etkf.py
pytassim/assimilation/filter/etkf_core.py
pytassim/assimilation/filter/filter.py
pytassim/assimilation/filter/ketkf.py
pytassim/assimilation/filter/ketkf_core.py
pytassim/assimilation/filter/letkf.py
pytassim/assimilation/filter/letkf_core.py
pytassim/assimilation/filter/letkf_dist.py
pytassim/assimilation/neural/__init__.py
pytassim/assimilation/neural/neural.py
pytassim/assimilation/variational/__init__.py
pytassim/assimilation/variational/variational.py
pytassim/kernels/__init__.py
pytassim/kernels/base_kernels.py
pytassim/kernels/diag.py
pytassim/kernels/linear.py
pytassim/kernels/module_kernel.py
pytassim/kernels/orn_uhl.py
pytassim/kernels/periodic.py
pytassim/kernels/polynomial.py
pytassim/kernels/rational.py
pytassim/kernels/rbf.py
pytassim/kernels/scale.py
pytassim/kernels/tanh.py
pytassim/kernels/utils.py
pytassim/localization/__init__.py
pytassim/localization/gaspari_cohn.py
pytassim/localization/localization.py
pytassim/model/__init__.py
pytassim/model/integration/__init__.py
pytassim/model/integration/integrator.py
pytassim/model/integration/rk4.py
pytassim/model/lorenz_84/__init__.py
pytassim/model/lorenz_84/lorenz_84.py
pytassim/model/lorenz_96/__init__.py
pytassim/model/lorenz_96/forward_model.py
pytassim/model/lorenz_96/lorenz_96.py
pytassim/model/terrsysmp/__init__.py
pytassim/model/terrsysmp/clm.py
pytassim/model/terrsysmp/common.py
pytassim/model/terrsysmp/cosmo.py
pytassim/obs_ops/__init__.py
pytassim/obs_ops/base_ops.py
pytassim/obs_ops/lorenz_96/__init__.py
pytassim/obs_ops/lorenz_96/bernoulli.py
pytassim/obs_ops/lorenz_96/identity.py
pytassim/obs_ops/terrsysmp/__init__.py
pytassim/obs_ops/terrsysmp/cos_t2m.py
pytassim/testing/__init__.py
pytassim/testing/decorators.py
torch_assimilate.egg-info/PKG-INFO
torch_assimilate.egg-info/SOURCES.txt
torch_assimilate.egg-info/dependency_links.txt
torch_assimilate.egg-info/top_level.txt