Metadata-Version: 2.1
Name: torch-assimilate
Version: 0.2.1
Summary: torch-assimilate is a data assimilation package based on PyTorch, xarray and dask
Home-page: https://gitlab.com/tobifinn/torch-assimilate
Author: Tobias Sebastian Finn
Author-email: tobias.sebastian.finn@uni-hamburg.de
License: GPL3
Keywords: statistics meteorology pre-processing testbed forecast assimilation data
Platform: UNKNOWN
